dyte_cli_package/__init__.py
dyte_cli_package/dyte.py
Dyte_Dependency_version_checker-1.0.4.dist-info/LICENSE.txt
Dyte_Dependency_version_checker-1.0.4.dist-info/METADATA
Dyte_Dependency_version_checker-1.0.4.dist-info/WHEEL
Dyte_Dependency_version_checker-1.0.4.dist-info/entry_points.txt
Dyte_Dependency_version_checker-1.0.4.dist-info/top_level.txt
Dyte_Dependency_version_checker-1.0.4.dist-info/RECORD
