Metadata-Version: 2.1
Name: Dyte-Dependency-version-checker
Version: 1.0.4
Summary: Demo Package for Dependency version checker for nodeJS and Python.
Home-page: https://github.com/dyte-submissions/dyte-vit-2022-harshkanani014
Author: Harsh Kanani
Author-email: harshkanani@gmail.com
License: MIT
Keywords: python package by Harsh Kanani
Platform: UNKNOWN
Classifier: Programming Language :: Python :: 3
Classifier: License :: OSI Approved :: MIT License
Classifier: Operating System :: OS Independent
Requires-Dist: bleach (==5.0.0)
Requires-Dist: certifi (==2022.5.18.1)
Requires-Dist: cffi (==1.15.0)
Requires-Dist: charset-normalizer (==2.0.12)
Requires-Dist: click (==8.1.3)
Requires-Dist: colorama (==0.4.4)
Requires-Dist: commonmark (==0.9.1)
Requires-Dist: Deprecated (==1.2.13)
Requires-Dist: docutils (==0.18.1)
Requires-Dist: Dyte-Dependency-version-checker (==1.0.1)
Requires-Dist: idna (==3.3)
Requires-Dist: importlib-metadata (==4.11.4)
Requires-Dist: keyring (==23.5.1)
Requires-Dist: pkginfo (==1.8.2)
Requires-Dist: progress (==1.6)
Requires-Dist: pycparser (==2.21)
Requires-Dist: pyfiglet (==0.8.post1)
Requires-Dist: PyGithub (==1.55)
Requires-Dist: Pygments (==2.12.0)
Requires-Dist: PyJWT (==2.4.0)
Requires-Dist: PyNaCl (==1.5.0)
Requires-Dist: pywin32-ctypes (==0.2.0)
Requires-Dist: readme-renderer (==35.0)
Requires-Dist: requests (==2.27.1)
Requires-Dist: requests-toolbelt (==0.9.1)
Requires-Dist: rfc3986 (==2.0.0)
Requires-Dist: rich (==12.4.4)
Requires-Dist: six (==1.16.0)
Requires-Dist: twine (==4.0.1)
Requires-Dist: typing-extensions (==4.2.0)
Requires-Dist: urllib3 (==1.26.9)
Requires-Dist: webencodings (==0.5.1)
Requires-Dist: wrapt (==1.14.1)
Requires-Dist: zipp (==3.8.0)
